{
    "molecular_geometry": {
        "z-matrix": [
            "\nLi\nH 1 1.0\nsymmetry c1\n",
            "\nLi\nH 1 1.1\nsymmetry c1\n",
            "\nLi\nH 1 1.2\nsymmetry c1\n",
            "\nLi\nH 1 1.3\nsymmetry c1\n",
            "\nLi\nH 1 1.4\nsymmetry c1\n",
            "\nLi\nH 1 1.5\nsymmetry c1\n",
            "\nLi\nH 1 1.6\nsymmetry c1\n",
            "\nLi\nH 1 1.7000000000000002\nsymmetry c1\n",
            "\nLi\nH 1 1.8\nsymmetry c1\n",
            "\nLi\nH 1 1.9\nsymmetry c1\n",
            "\nLi\nH 1 2.0\nsymmetry c1\n",
            "\nLi\nH 1 2.1\nsymmetry c1\n",
            "\nLi\nH 1 2.2\nsymmetry c1\n",
            "\nLi\nH 1 2.3\nsymmetry c1\n",
            "\nLi\nH 1 2.4000000000000004\nsymmetry c1\n",
            "\nLi\nH 1 2.5\nsymmetry c1\n",
            "\nLi\nH 1 2.6\nsymmetry c1\n",
            "\nLi\nH 1 2.7\nsymmetry c1\n",
            "\nLi\nH 1 2.8\nsymmetry c1\n",
            "\nLi\nH 1 2.9000000000000004\nsymmetry c1\n",
            "\nLi\nH 1 3.0\nsymmetry c1\n"
        ]
    },
    "return_results": {
        "casci_energies": [
            [
                -7.88365096799119,
                -7.764131001534703,
                -7.731472308210349
            ],
            [
                -7.9233857802230325,
                -7.803865520474189,
                -7.767952821125427
            ],
            [
                -7.9496967348169205,
                -7.830289769770398,
                -7.793603562899492
            ],
            [
                -7.966394905737418,
                -7.847216174986066,
                -7.811500274899354
            ],
            [
                -7.976202759342142,
                -7.857393872709538,
                -7.823765923853278
            ],
            [
                -7.981073677420954,
                -7.862828265557694,
                -7.831876894487803
            ],
            [
                -7.9824186268884025,
                -7.865015989726815,
                -7.836850670978747
            ],
            [
                -7.981264162439647,
                -7.865111621056631,
                -7.839365102318945
            ],
            [
                -7.97836249721282,
                -7.864031403445322,
                -7.839850916824495
            ],
            [
                -7.974268751620537,
                -7.862482630857299,
                -7.838598838140309
            ],
            [
                -7.969395839829401,
                -7.860932694308521,
                -7.83588667271651
            ],
            [
                -7.964054205213343,
                -7.859604783537729,
                -7.832052349152986
            ],
            [
                -7.958481255925655,
                -7.858558772435707,
                -7.827462991935706
            ],
            [
                -7.952863440113405,
                -7.857790690019935,
                -7.822451709462438
            ],
            [
                -7.947352275561528,
                -7.857283736172138,
                -7.817291224072697
            ],
            [
                -7.942074362201395,
                -7.857016847560087,
                -7.812198406506709
            ],
            [
                -7.9371346927960955,
                -7.85695651680275,
                -7.807343942468944
            ],
            [
                -7.932612920836159,
                -7.85704671491425,
                -7.802854870945893
            ],
            [
                -7.928554187089917,
                -7.857204223079551,
                -7.798810316606901
            ],
            [
                -7.9249593602783275,
                -7.857323640535446,
                -7.795237773968823
            ],
            [
                -7.921781880532382,
                -7.857292298008952,
                -7.79211884762185
            ]
        ],
        "casscf_energies": [
            [
                -7.915818577549953,
                -7.79800269026579,
                -7.779621067633081
            ],
            [
                -7.95503271263596,
                -7.837175393339263,
                -7.815919551584032
            ],
            [
                -7.981093961490616,
                -7.8635564180100905,
                -7.841042238033178
            ],
            [
                -7.997662080692762,
                -7.881078760366006,
                -7.858606716383147
            ],
            [
                -8.007762068868683,
                -7.892123964677871,
                -7.8700784053189325
            ],
            [
                -8.013094830975444,
                -7.898805976865073,
                -7.877257240225598
            ],
            [
                -8.015036535420922,
                -7.9026010156100455,
                -7.8811726814522745
            ],
            [
                -8.014586988389656,
                -7.904585459158398,
                -7.8825541455960195
            ],
            [
                -8.012477629779898,
                -7.905493494159626,
                -7.881972007236623
            ],
            [
                -8.009244082955586,
                -7.905776588718254,
                -7.879917352796009
            ],
            [
                -8.005277704207595,
                -7.905688809428488,
                -7.876813802877126
            ],
            [
                -8.000862874425465,
                -7.905368723588892,
                -7.873005177172756
            ],
            [
                -7.996204700191591,
                -7.9048928092135125,
                -7.86875370892482
            ],
            [
                -7.991450254172641,
                -7.9043029080156915,
                -7.864251948340824
            ],
            [
                -7.986704680050173,
                -7.903619900641763,
                -7.859639771341233
            ],
            [
                -7.981662014991106,
                -7.9028038302421875,
                -7.8678659057991105
            ],
            [
                -7.977521922217626,
                -7.901994563404849,
                -7.850473035321278
            ],
            [
                -7.97317982538962,
                -7.9010438614671035,
                -7.846062617316254
            ],
            [
                -7.969047090195218,
                -7.8999885290002485,
                -7.841847361347132
            ],
            [
                -7.965145306424266,
                -7.898817050306587,
                -7.837884366403957
            ],
            [
                -7.961282213004793,
                -7.89742202701105,
                -7.867248265940086
            ]
        ]
    },
    "molecule_id": "LiH",
    "omega_value": 0.12086,
    "lambda_vector": [
        0,
        0,
        0.05
    ],
    "ci_level": "cas",
    "ignore_coupling": false,
    "number_of_photons": 1,
    "natural_orbitals": false,
    "photon_number_basis": false,
    "canonical_mos": false,
    "coherent_state_basis": true,
    "davidson_roots": 3,
    "davidson_threshold": 1e-05,
    "davidson_maxdim": 20,
    "spin_adaptation": "singlet",
    "davidson_maxiter": 100,
    "davidson_indim": 8,
    "test_mode": false,
    "nact_orbs": 9,
    "nact_els": 4,
    "basis": "6-311g",
    "scf_type": "pk",
    "e_convergence": 1e-10,
    "d_convergence": 1e-10
}
